adnbidder/__init__.py
adnbidder/bidder.py
adnbidder-1.0.7.dist-info/LICENSE.txt
adnbidder-1.0.7.dist-info/METADATA
adnbidder-1.0.7.dist-info/WHEEL
adnbidder-1.0.7.dist-info/top_level.txt
adnbidder-1.0.7.dist-info/RECORD
